cide/__init__.py
cide/clients.py
cide/clocked.py
cide/command.py
cide/decoder.py
cide/default.py
cide/encoder.py
cide/handler.py
cide/listens.py
cide/message.py
cide/objects.py
cide/storage.py
cide/threads.py
cide/utility.py
cide/modules/__init__.py
cide/modules/cmd.py
cide/modules/irc.py
cide/modules/log.py
cide/modules/mdl.py
cide/modules/req.py
cide/modules/rss.py
cide/modules/tdo.py
cide-1.data/scripts/cide
cide-1.data/scripts/cidec
cide-1.data/scripts/cided
cide-1.dist-info/METADATA
cide-1.dist-info/WHEEL
cide-1.dist-info/top_level.txt
cide-1.dist-info/RECORD
