Metadata-Version: 2.1
Name: cide
Version: 1
Summary: object programming bot
Home-page: http://github.com/operbot/operbot
Author: B.H.J. Thate
Author-email: operbot100@gmail.com
License: Public Domain
Platform: UNKNOWN
Classifier: Development Status :: 3 - Alpha
Classifier: License :: Public Domain
Classifier: Operating System :: POSIX :: Linux
Classifier: Programming Language :: Python :: 3 :: Only
Classifier: Intended Audience :: System Administrators
Classifier: Topic :: Communications :: Chat :: Internet Relay Chat
Classifier: Topic :: Software Development :: Libraries :: Python Modules
